aexpect/__init__.py
aexpect/client.py
aexpect/exceptions.py
aexpect/ops_linux.py
aexpect/ops_windows.py
aexpect/remote.py
aexpect/remote_door.py
aexpect/rss_client.py
aexpect/shared.py
aexpect/utils/__init__.py
aexpect/utils/astring.py
aexpect/utils/data_factory.py
aexpect/utils/path.py
aexpect/utils/process.py
aexpect/utils/wait.py
aexpect-1.8.0.data/scripts/aexpect_helper
aexpect-1.8.0.dist-info/LICENSE
aexpect-1.8.0.dist-info/METADATA
aexpect-1.8.0.dist-info/WHEEL
aexpect-1.8.0.dist-info/top_level.txt
aexpect-1.8.0.dist-info/RECORD
