Metadata-Version: 2.1
Name: aexpect
Version: 1.8.0
Summary: Aexpect
Home-page: http://avocado-framework.github.io/
Author: Aexpect developers
Author-email: avocado-devel@redhat.com
License: GPLv2+
Classifier: Development Status :: 6 - Mature
Classifier: License :: OSI Approved :: GNU General Public License v2 or later (GPLv2+)
Classifier: Natural Language :: English
Classifier: Operating System :: POSIX
Classifier: Programming Language :: Python :: 3
License-File: LICENSE
